LICENSE.txt
MANIFEST.in
README.rst
requirements.txt
setup.cfg
setup.py
doc/Makefile
doc/conf.py
doc/index.rst
doc/objects.inv
doc/yoda.1
doc/rst/install.rst
doc/rst/module.rst
doc/rst/refman.rst
doc/rst/tutor.rst
doc/rst/install/extensions.rst
doc/rst/install/ext/yoda.rst
doc/rst/module/extensions.rst
doc/rst/module/ext/yoda/main.rst
doc/rst/module/ext/yoda/testengine.rst
doc/rst/module/ext/yoda/testobject.rst
doc/rst/module/ext/yoda/testresults.rst
doc/rst/module/ext/yoda/util.rst
doc/rst/module/ext/yoda/yoda.rst
doc/rst/refman/ext/yoda.rst
doc/rst/tutor/extensions.rst
doc/rst/tutor/ext/yoda/tut1_script.rst
doc/rst/tutor/ext/yoda/tut2_execution.rst
doc/rst/tutor/ext/yoda/tut3_reporting.rst
doc/rst/tutor/ext/yoda/tut4_hlp_lib.rst
doc/rst/tutor/ext/yoda/tut5_chain.rst
doc/rst/tutor/ext/yoda/tut6_break.rst
doc/rst/tutor/ext/yoda/tut7_parallel.rst
doc/rst/tutor/ext/yoda/tut8_util.rst
doc/rst/tutor/ext/yoda/yoda.rst
etc/hydratk/conf.d/hydratk-ext-yoda.conf
src/hydratk/__init__.py
src/hydratk/extensions/__init__.py
src/hydratk/extensions/yoda/__init__.py
src/hydratk/extensions/yoda/bootstrapper.py
src/hydratk/extensions/yoda/testengine.py
src/hydratk/extensions/yoda/testobject.py
src/hydratk/extensions/yoda/yoda.py
src/hydratk/extensions/yoda/testresults/__init__.py
src/hydratk/extensions/yoda/testresults/testresults.py
src/hydratk/extensions/yoda/testresults/handlers/__init__.py
src/hydratk/extensions/yoda/testresults/handlers/console.py
src/hydratk/extensions/yoda/testresults/handlers/html.py
src/hydratk/extensions/yoda/testresults/handlers/junit.py
src/hydratk/extensions/yoda/testresults/handlers/text.py
src/hydratk/extensions/yoda/testresults/handlers/xjunit/__init__.py
src/hydratk/extensions/yoda/testresults/handlers/xjunit/testcase.py
src/hydratk/extensions/yoda/testresults/handlers/xjunit/testreport.py
src/hydratk/extensions/yoda/testresults/handlers/xjunit/testsuite.py
src/hydratk/extensions/yoda/testresults/handlers/xjunit/utils.py
src/hydratk_ext_yoda.egg-info/PKG-INFO
src/hydratk_ext_yoda.egg-info/SOURCES.txt
src/hydratk_ext_yoda.egg-info/dependency_links.txt
src/hydratk_ext_yoda.egg-info/entry_points.txt
src/hydratk_ext_yoda.egg-info/not-zip-safe
src/hydratk_ext_yoda.egg-info/top_level.txt
